telnet/__init__.py
telnet/telnet.py
PyTelnet-1.0.1.dist-info/LICENSE
PyTelnet-1.0.1.dist-info/METADATA
PyTelnet-1.0.1.dist-info/WHEEL
PyTelnet-1.0.1.dist-info/top_level.txt
PyTelnet-1.0.1.dist-info/RECORD
