Metadata-Version: 2.1
Name: PyTelnet
Version: 1.0.1
Summary: A small package for sending and recieving commands per tcp
Home-page: https://github.com/SilvanKohler/PyTelnet
Author: Silvan Kohler
Author-email: edu.silvan.kohler@gmail.com
License: UNKNOWN
Platform: UNKNOWN
Classifier: Programming Language :: Python :: 3
Classifier: License :: OSI Approved :: MIT License
Classifier: Operating System :: OS Independent
